LICENSE
MANIFEST.in
README.rst
setup.py
wagtail_gallery/__init__.py
wagtail_gallery/admin.py
wagtail_gallery/apps.py
wagtail_gallery/managers.py
wagtail_gallery/models.py
wagtail_gallery/tests.py
wagtail_gallery/views.py
wagtail_gallery/wagtail_hooks.py
wagtail_gallery.egg-info/PKG-INFO
wagtail_gallery.egg-info/SOURCES.txt
wagtail_gallery.egg-info/dependency_links.txt
wagtail_gallery.egg-info/requires.txt
wagtail_gallery.egg-info/top_level.txt
wagtail_gallery/__pycache__/__init__.cpython-36.pyc
wagtail_gallery/__pycache__/admin.cpython-36.pyc
wagtail_gallery/__pycache__/managers.cpython-36.pyc
wagtail_gallery/__pycache__/models.cpython-36.pyc
wagtail_gallery/__pycache__/wagtail_hooks.cpython-36.pyc
wagtail_gallery/docs/Makefile
wagtail_gallery/docs/source/api.rst
wagtail_gallery/docs/source/changelog.rst
wagtail_gallery/docs/source/conf.py
wagtail_gallery/docs/source/customising.rst
wagtail_gallery/docs/source/getting-started.rst
wagtail_gallery/docs/source/index.rst
wagtail_gallery/docs/source/internationalisation.rst
wagtail_gallery/docs/source/requirements.txt
wagtail_gallery/docs/source/roadmap.rst
wagtail_gallery/locale/af/LC_MESSAGES/django.mo
wagtail_gallery/locale/af/LC_MESSAGES/django.po
wagtail_gallery/migrations/0001_initial.py
wagtail_gallery/migrations/__init__.py
wagtail_gallery/migrations/__pycache__/0001_initial.cpython-36.pyc
wagtail_gallery/migrations/__pycache__/__init__.cpython-36.pyc
wagtail_gallery/static/wagtail_gallery/css/all.css
wagtail_gallery/static/wagtail_gallery/css/bootstrap.min.css
wagtail_gallery/static/wagtail_gallery/css/custom.css
wagtail_gallery/static/wagtail_gallery/css/lightbox.min.css
wagtail_gallery/static/wagtail_gallery/images/close.png
wagtail_gallery/static/wagtail_gallery/images/loading.gif
wagtail_gallery/static/wagtail_gallery/images/next.png
wagtail_gallery/static/wagtail_gallery/images/prev.png
wagtail_gallery/static/wagtail_gallery/js/bootstrap.bundle.min.js
wagtail_gallery/static/wagtail_gallery/js/jquery.min.js
wagtail_gallery/static/wagtail_gallery/js/lightbox.min.js
wagtail_gallery/static/wagtail_gallery/webfonts/fa-brands-400.eot
wagtail_gallery/static/wagtail_gallery/webfonts/fa-brands-400.svg
