Metadata-Version: 2.1
Name: wagtail_gallery
Version: 0.1.1
Summary: A simple gallery app built for Wagtail CMS and Django
Home-page: https://gitlab.com/dfmeyer/wagtail_gallery
Author: Daniel F. Meyer
Author-email: me3064@gmail.com
License: MIT
Project-URL: Bug Tracker, https://gitlab.com/dfmeyer/wagtail_gallery/issues
Project-URL: Documentation, https://wagtail-gallery.readthedocs.io/en/latest/
Project-URL: Source Code, https://gitlab.com/dfmeyer/wagtail_gallery
Keywords: Django,Wagtail,gallery
Platform: UNKNOWN
Requires-Python: >=3.5
